thread_task/__init__.py
thread_task/constants.py
thread_task/functions.py
thread_task/periodic.py
thread_task/repeated.py
thread_task/sleep.py
thread_task/task.py
thread_task-0.9.7.dist-info/LICENSE
thread_task-0.9.7.dist-info/METADATA
thread_task-0.9.7.dist-info/WHEEL
thread_task-0.9.7.dist-info/top_level.txt
thread_task-0.9.7.dist-info/RECORD
