Metadata-Version: 1.2
Name: thread-task
Version: 0.9.7
Summary: organize and run thread tasks
Home-page: https://github.com/ChristophGaukel/thread_task
Author: Christoph Gaukel
Author-email: christoph.gaukel@gmx.de
License: UNKNOWN
Platform: UNKNOWN
Classifier: Programming Language :: Python :: 3
Classifier: License :: OSI Approved :: GNU General Public License v3 or later (GPLv3+)
Classifier: Operating System :: OS Independent
Requires-Python: >=3.3
